vin_parser/__init__.py
vin_parser/core.py
vin_parser/nhtsa.py
vin_parser/data/wmi.csv
vin_parser-0.0.1.dist-info/LICENCE.md
vin_parser-0.0.1.dist-info/METADATA
vin_parser-0.0.1.dist-info/WHEEL
vin_parser-0.0.1.dist-info/top_level.txt
vin_parser-0.0.1.dist-info/RECORD
