Metadata-Version: 2.1
Name: vin-parser
Version: 0.0.1
Summary: This is vin-parser package description
Home-page: https://github.com/nighcoder/vin-parser
Author: Daniel Ciumberică
Author-email: ciumbi.ionut@gmail.com
License: MIT
Keywords: VIN,WMI,VDS,OBD
Platform: UNKNOWN
Classifier: Development Status :: 3 - Alpha
Classifier: Intended Audience :: Developers
Classifier: License :: OSI Approved :: MIT License
Classifier: Operating System :: OS Independent
Classifier: Programming Language :: Python :: 3
Classifier: Programming Language :: Python :: 3.6
Classifier: Topic :: Software Development
Classifier: Topic :: Utilities
Requires-Dist: requests (==2.22.0)
